fascraft/__init__.py
fascraft/commands/__init__.py
fascraft/commands/analyze.py
fascraft/commands/analyze_dependencies.py
fascraft/commands/ci_cd.py
fascraft/commands/config.py
fascraft/commands/dependencies.py
fascraft/commands/deploy.py
fascraft/commands/dockerize.py
fascraft/commands/docs.py
fascraft/commands/environment.py
fascraft/commands/generate.py
fascraft/commands/generate_test.py
fascraft/commands/list.py
fascraft/commands/list_templates.py
fascraft/commands/migrate.py
fascraft/commands/new.py
fascraft/commands/remove.py
fascraft/commands/update.py
fascraft/exceptions.py
fascraft/main.py
fascraft/module_dependencies.py
fascraft/template_registry.py
fascraft/templates/documentation/API_documentation.md.jinja2
fascraft/templates/documentation/CHANGELOG_template.md.jinja2
fascraft/templates/documentation/module_overview.md.jinja2
fascraft/templates/documentation/project_overview.md.jinja2
fascraft/templates/documentation/README_template.md.jinja2
fascraft/templates/module/__init__.py.jinja2
fascraft/templates/module/model.py.jinja2
fascraft/templates/module/models.py.jinja2
fascraft/templates/module/router.py.jinja2
fascraft/templates/module/routers.py.jinja2
fascraft/templates/module/schemas.py.jinja2
fascraft/templates/module/service.py.jinja2
fascraft/templates/module/services.py.jinja2
fascraft/templates/module/tests/__init__.py.jinja2
fascraft/templates/module/tests/test_models.py.jinja2
fascraft/templates/module_templates/admin_panel/__init__.py.jinja2
fascraft/templates/module_templates/admin_panel/models.py.jinja2
fascraft/templates/module_templates/admin_panel/routers.py.jinja2
fascraft/templates/module_templates/admin_panel/schemas.py.jinja2
fascraft/templates/module_templates/admin_panel/services.py.jinja2
fascraft/templates/module_templates/admin_panel/tests/__init__.py.jinja2
fascraft/templates/module_templates/admin_panel/tests/test_models.py.jinja2
fascraft/templates/module_templates/api_first/__init__.py.jinja2
fascraft-0.4.2.dist-info/entry_points.txt
fascraft-0.4.2.dist-info/METADATA
fascraft-0.4.2.dist-info/WHEEL
fascraft-0.4.2.dist-info/RECORD
