Metadata-Version: 2.3
Name: fascraft
Version: 0.4.2
Summary: A CLI for generating modular FastAPI projects with environment and dependency management
License: MIT
Author: Lutor Iyornumbe
Author-email: biggestluey@gmail.com
Requires-Python: >=3.10,<4.0
Classifier: License :: OSI Approved :: MIT License
Classifier: Programming Language :: Python :: 3
Classifier: Programming Language :: Python :: 3.10
Classifier: Programming Language :: Python :: 3.11
Classifier: Programming Language :: Python :: 3.12
Classifier: Programming Language :: Python :: 3.13
Requires-Dist: jinja2 (>=3.1.0,<4.0.0)
Requires-Dist: pyyaml (>=6.0.2,<7.0.0)
Requires-Dist: rich (>=14.0.0,<15.0.0)
Requires-Dist: tomli (>=1.2.3,<2.0.0)
Requires-Dist: tomli-w (>=1.0.0,<2.0.0)
Requires-Dist: typer (>=0.16.0,<0.17.0)
